neuro_config_client/__init__.py
neuro_config_client/client.py
neuro_config_client/entities.py
neuro_config_client/factories.py
neuro_config_client/py.typed
neuro_config_client-25.12.0.dist-info/licenses/LICENSE
neuro_config_client-25.12.0.dist-info/METADATA
neuro_config_client-25.12.0.dist-info/WHEEL
neuro_config_client-25.12.0.dist-info/top_level.txt
neuro_config_client-25.12.0.dist-info/RECORD
